sensorpush_ble/__init__.py
sensorpush_ble/parser.py
sensorpush_ble/py.typed
sensorpush_ble-1.8.0.dist-info/LICENSE
sensorpush_ble-1.8.0.dist-info/METADATA
sensorpush_ble-1.8.0.dist-info/WHEEL
sensorpush_ble-1.8.0.dist-info/RECORD
